chemcell/__init__.py
chemcell/chemcell.py
chemcell/config.py
chemcell/data_sources.py
chemcell/post_process.py
chemcell/process.py
chemcell/scrape.py
chemcell/utlity.py
chemcell-0.2.5.dist-info/LICENSE
chemcell-0.2.5.dist-info/METADATA
chemcell-0.2.5.dist-info/WHEEL
chemcell-0.2.5.dist-info/top_level.txt
chemcell-0.2.5.dist-info/RECORD
